iiif/__init__.py
iiif/_version.py
iiif/auth.py
iiif/auth_basic.py
iiif/auth_clickthrough.py
iiif/auth_external.py
iiif/auth_flask.py
iiif/auth_google.py
iiif/auth_kiosk.py
iiif/error.py
iiif/flask_utils.py
iiif/info.py
iiif/manipulator.py
iiif/manipulator_gen.py
iiif/manipulator_netpbm.py
iiif/manipulator_pil.py
iiif/request.py
iiif/static.py
iiif/templates/static_osd.html
iiif/templates/static_osd.html~
iiif/templates/testserver_osd.html
iiif/templates/testserver_osd.html~
iiif/third_party/jquery-1.11.1.min.js
iiif/third_party/openseadragon100/openseadragon.min.js
iiif/third_party/openseadragon100/images/fullpage_grouphover.png
iiif/third_party/openseadragon100/images/fullpage_hover.png
iiif/third_party/openseadragon100/images/fullpage_pressed.png
iiif/third_party/openseadragon100/images/fullpage_rest.png
iiif/third_party/openseadragon100/images/home_grouphover.png
iiif/third_party/openseadragon100/images/home_hover.png
iiif/third_party/openseadragon100/images/home_pressed.png
iiif/third_party/openseadragon100/images/home_rest.png
iiif/third_party/openseadragon100/images/next_grouphover.png
iiif/third_party/openseadragon100/images/next_hover.png
iiif/third_party/openseadragon100/images/next_pressed.png
iiif/third_party/openseadragon100/images/next_rest.png
iiif/third_party/openseadragon100/images/previous_grouphover.png
iiif/third_party/openseadragon100/images/previous_hover.png
iiif/third_party/openseadragon100/images/previous_pressed.png
iiif/third_party/openseadragon100/images/previous_rest.png
iiif/third_party/openseadragon100/images/rotateleft_grouphover.png
iiif/third_party/openseadragon100/images/rotateleft_hover.png
iiif/third_party/openseadragon100/images/rotateleft_pressed.png
iiif/third_party/openseadragon100/images/rotateleft_rest.png
iiif/third_party/openseadragon100/images/rotateright_grouphover.png
iiif/third_party/openseadragon100/images/rotateright_hover.png
iiif/third_party/openseadragon100/images/rotateright_pressed.png
iiif-1.0.10.dist-info/LICENSE.txt
iiif-1.0.10.dist-info/METADATA
iiif-1.0.10.dist-info/WHEEL
iiif-1.0.10.dist-info/pbr.json
iiif-1.0.10.dist-info/top_level.txt
iiif-1.0.10.dist-info/RECORD
